[
  {
    "algo": "blake2b512",
    "block_size": 16,
    "speed": 503062506.67
  },
  {
    "algo": "blake2b512",
    "block_size": 64,
    "speed": 2015492480.01
  },
  {
    "algo": "blake2b512",
    "block_size": 256,
    "speed": 5639077205.34
  },
  {
    "algo": "blake2b512",
    "block_size": 1024,
    "speed": 8225234261.33
  },
  {
    "algo": "blake2b512",
    "block_size": 8192,
    "speed": 9497146709.35
  },
  {
    "algo": "blake2b512",
    "block_size": 16384,
    "speed": 9631569237.34
  },
  {
    "algo": "sha256",
    "block_size": 16,
    "speed": 637670384.02
  },
  {
    "algo": "sha256",
    "block_size": 64,
    "speed": 1662905194.68
  },
  {
    "algo": "sha256",
    "block_size": 256,
    "speed": 3508997887.99
  },
  {
    "algo": "sha256",
    "block_size": 1024,
    "speed": 4730379264.0
  },
  {
    "algo": "sha256",
    "block_size": 8192,
    "speed": 5305338538.66
  },
  {
    "algo": "sha256",
    "block_size": 16384,
    "speed": 5363542698.67
  },
  {
    "algo": "sha512",
    "block_size": 16,
    "speed": 482075292.06
  },
  {
    "algo": "sha512",
    "block_size": 64,
    "speed": 1929717845.33
  },
  {
    "algo": "sha512",
    "block_size": 256,
    "speed": 3913292373.33
  },
  {
    "algo": "sha512",
    "block_size": 1024,
    "speed": 6413475839.99
  },
  {
    "algo": "sha512",
    "block_size": 8192,
    "speed": 7919849567.27
  },
  {
    "algo": "sha512",
    "block_size": 16384,
    "speed": 8046329855.99
  },
  {
    "algo": "sha3-256",
    "block_size": 16,
    "speed": 330666815.99
  },
  {
    "algo": "sha3-256",
    "block_size": 64,
    "speed": 1325641343.99
  },
  {
    "algo": "sha3-256",
    "block_size": 256,
    "speed": 3161672703.99
  },
  {
    "algo": "sha3-256",
    "block_size": 1024,
    "speed": 3640006656.0
  },
  {
    "algo": "sha3-256",
    "block_size": 8192,
    "speed": 4058150229.31
  },
  {
    "algo": "sha3-256",
    "block_size": 16384,
    "speed": 4096764586.67
  },
  {
    "algo": "sha3-512",
    "block_size": 16,
    "speed": 339154554.67
  },
  {
    "algo": "sha3-512",
    "block_size": 64,
    "speed": 1362428928.0
  },
  {
    "algo": "sha3-512",
    "block_size": 256,
    "speed": 1867942912.0
  },
  {
    "algo": "sha3-512",
    "block_size": 1024,
    "speed": 2170087424.0
  },
  {
    "algo": "sha3-512",
    "block_size": 8192,
    "speed": 2350825472.01
  },
  {
    "algo": "sha3-512",
    "block_size": 16384,
    "speed": 2356640612.64
  },
  {
    "algo": "shake128",
    "block_size": 16,
    "speed": 412476346.67
  },
  {
    "algo": "shake128",
    "block_size": 64,
    "speed": 1669198570.66
  },
  {
    "algo": "shake128",
    "block_size": 256,
    "speed": 3703329365.33
  },
  {
    "algo": "shake128",
    "block_size": 1024,
    "speed": 4563415722.67
  },
  {
    "algo": "shake128",
    "block_size": 8192,
    "speed": 5413483861.33
  },
  {
    "algo": "shake128",
    "block_size": 16384,
    "speed": 5321818111.99
  },
  {
    "algo": "shake256",
    "block_size": 16,
    "speed": 415604074.66
  },
  {
    "algo": "shake256",
    "block_size": 64,
    "speed": 1668546197.34
  },
  {
    "algo": "shake256",
    "block_size": 256,
    "speed": 3712898730.66
  },
  {
    "algo": "shake256",
    "block_size": 1024,
    "speed": 4056932693.34
  },
  {
    "algo": "shake256",
    "block_size": 8192,
    "speed": 4381712384.01
  },
  {
    "algo": "shake256",
    "block_size": 16384,
    "speed": 4457627648.0
  },
  {
    "algo": "AES-256-CBC",
    "block_size": 16,
    "speed": 8441160944.01
  },
  {
    "algo": "AES-256-CBC",
    "block_size": 64,
    "speed": 11396302250.67
  },
  {
    "algo": "AES-256-CBC",
    "block_size": 256,
    "speed": 11564287232.0
  },
  {
    "algo": "AES-256-CBC",
    "block_size": 1024,
    "speed": 11635915434.68
  },
  {
    "algo": "AES-256-CBC",
    "block_size": 8192,
    "speed": 11661219157.34
  },
  {
    "algo": "AES-256-CBC",
    "block_size": 16384,
    "speed": 11678924800.0
  },
  {
    "algo": "ARIA-256-CBC",
    "block_size": 16,
    "speed": 1225142042.67
  },
  {
    "algo": "ARIA-256-CBC",
    "block_size": 64,
    "speed": 1306743338.66
  },
  {
    "algo": "ARIA-256-CBC",
    "block_size": 256,
    "speed": 1329104725.34
  },
  {
    "algo": "ARIA-256-CBC",
    "block_size": 1024,
    "speed": 1344050517.33
  },
  {
    "algo": "ARIA-256-CBC",
    "block_size": 8192,
    "speed": 1352403626.69
  },
  {
    "algo": "ARIA-256-CBC",
    "block_size": 16384,
    "speed": 1358035649.35
  },
  {
    "algo": "CAMELLIA-256-CBC",
    "block_size": 16,
    "speed": 1127335858.95
  },
  {
    "algo": "CAMELLIA-256-CBC",
    "block_size": 64,
    "speed": 1620296639.99
  },
  {
    "algo": "CAMELLIA-256-CBC",
    "block_size": 256,
    "speed": 1810294954.66
  },
  {
    "algo": "CAMELLIA-256-CBC",
    "block_size": 1024,
    "speed": 1874811562.68
  },
  {
    "algo": "CAMELLIA-256-CBC",
    "block_size": 8192,
    "speed": 1892092586.67
  },
  {
    "algo": "CAMELLIA-256-CBC",
    "block_size": 16384,
    "speed": 1891205120.0
  },
  {
    "algo": "SM4-CBC",
    "block_size": 16,
    "speed": 1372731456.0
  },
  {
    "algo": "SM4-CBC",
    "block_size": 64,
    "speed": 1441129834.67
  },
  {
    "algo": "SM4-CBC",
    "block_size": 256,
    "speed": 1460397482.68
  },
  {
    "algo": "SM4-CBC",
    "block_size": 1024,
    "speed": 1466765994.67
  },
  {
    "algo": "SM4-CBC",
    "block_size": 8192,
    "speed": 1468104704.01
  },
  {
    "algo": "SM4-CBC",
    "block_size": 16384,
    "speed": 1468612608.01
  }
]