[
  {
    "algo": "blake2b512",
    "block_size": 16,
    "speed": 2954696416.0
  },
  {
    "algo": "blake2b512",
    "block_size": 64,
    "speed": 11704833598.84
  },
  {
    "algo": "blake2b512",
    "block_size": 256,
    "speed": 31727915946.66
  },
  {
    "algo": "blake2b512",
    "block_size": 1024,
    "speed": 43136639317.32
  },
  {
    "algo": "blake2b512",
    "block_size": 8192,
    "speed": 48407087786.63
  },
  {
    "algo": "blake2b512",
    "block_size": 16384,
    "speed": 48838164480.0
  },
  {
    "algo": "sha256",
    "block_size": 16,
    "speed": 7034185642.67
  },
  {
    "algo": "sha256",
    "block_size": 64,
    "speed": 21976093440.0
  },
  {
    "algo": "sha256",
    "block_size": 256,
    "speed": 50086867968.02
  },
  {
    "algo": "sha256",
    "block_size": 1024,
    "speed": 73545525589.31
  },
  {
    "algo": "sha256",
    "block_size": 8192,
    "speed": 85218254848.0
  },
  {
    "algo": "sha256",
    "block_size": 16384,
    "speed": 86125335893.31
  },
  {
    "algo": "sha512",
    "block_size": 16,
    "speed": 3159373664.02
  },
  {
    "algo": "sha512",
    "block_size": 64,
    "speed": 12572483882.67
  },
  {
    "algo": "sha512",
    "block_size": 256,
    "speed": 22970230442.67
  },
  {
    "algo": "sha512",
    "block_size": 1024,
    "speed": 34909204480.02
  },
  {
    "algo": "sha512",
    "block_size": 8192,
    "speed": 40992290133.31
  },
  {
    "algo": "sha512",
    "block_size": 16384,
    "speed": 41505630890.64
  },
  {
    "algo": "sha3-256",
    "block_size": 16,
    "speed": 1926570741.35
  },
  {
    "algo": "sha3-256",
    "block_size": 64,
    "speed": 7635140949.34
  },
  {
    "algo": "sha3-256",
    "block_size": 256,
    "speed": 18155088213.35
  },
  {
    "algo": "sha3-256",
    "block_size": 1024,
    "speed": 21086305280.02
  },
  {
    "algo": "sha3-256",
    "block_size": 8192,
    "speed": 23024552618.68
  },
  {
    "algo": "sha3-256",
    "block_size": 16384,
    "speed": 23112062293.34
  },
  {
    "algo": "sha3-512",
    "block_size": 16,
    "speed": 1947815749.35
  },
  {
    "algo": "sha3-512",
    "block_size": 64,
    "speed": 7771428245.37
  },
  {
    "algo": "sha3-512",
    "block_size": 256,
    "speed": 10277302954.66
  },
  {
    "algo": "sha3-512",
    "block_size": 1024,
    "speed": 11948084565.34
  },
  {
    "algo": "sha3-512",
    "block_size": 8192,
    "speed": 12894445567.99
  },
  {
    "algo": "sha3-512",
    "block_size": 16384,
    "speed": 12924780544.03
  },
  {
    "algo": "shake128",
    "block_size": 16,
    "speed": 1934488794.66
  },
  {
    "algo": "shake128",
    "block_size": 64,
    "speed": 7901676117.33
  },
  {
    "algo": "shake128",
    "block_size": 256,
    "speed": 18653628501.33
  },
  {
    "algo": "shake128",
    "block_size": 1024,
    "speed": 24294112938.66
  },
  {
    "algo": "shake128",
    "block_size": 8192,
    "speed": 28456946346.7
  },
  {
    "algo": "shake128",
    "block_size": 16384,
    "speed": 28522184704.01
  },
  {
    "algo": "shake256",
    "block_size": 16,
    "speed": 1969732431.99
  },
  {
    "algo": "shake256",
    "block_size": 64,
    "speed": 7833184234.67
  },
  {
    "algo": "shake256",
    "block_size": 256,
    "speed": 18531877290.66
  },
  {
    "algo": "shake256",
    "block_size": 1024,
    "speed": 21629586432.01
  },
  {
    "algo": "shake256",
    "block_size": 8192,
    "speed": 23716397055.99
  },
  {
    "algo": "shake256",
    "block_size": 16384,
    "speed": 23985722709.33
  },
  {
    "algo": "AES-256-CBC",
    "block_size": 16,
    "speed": 41467865439.96
  },
  {
    "algo": "AES-256-CBC",
    "block_size": 64,
    "speed": 47210722175.99
  },
  {
    "algo": "AES-256-CBC",
    "block_size": 256,
    "speed": 48847740159.99
  },
  {
    "algo": "AES-256-CBC",
    "block_size": 1024,
    "speed": 49240124416.01
  },
  {
    "algo": "AES-256-CBC",
    "block_size": 8192,
    "speed": 49362217642.65
  },
  {
    "algo": "AES-256-CBC",
    "block_size": 16384,
    "speed": 49366013269.33
  },
  {
    "algo": "ARIA-256-CBC",
    "block_size": 16,
    "speed": 5788500629.35
  },
  {
    "algo": "ARIA-256-CBC",
    "block_size": 64,
    "speed": 5910216597.34
  },
  {
    "algo": "ARIA-256-CBC",
    "block_size": 256,
    "speed": 5937364138.68
  },
  {
    "algo": "ARIA-256-CBC",
    "block_size": 1024,
    "speed": 5941040127.99
  },
  {
    "algo": "ARIA-256-CBC",
    "block_size": 8192,
    "speed": 5943487146.66
  },
  {
    "algo": "ARIA-256-CBC",
    "block_size": 16384,
    "speed": 5943186773.3
  },
  {
    "algo": "CAMELLIA-256-CBC",
    "block_size": 16,
    "speed": 6449352202.65
  },
  {
    "algo": "CAMELLIA-256-CBC",
    "block_size": 64,
    "speed": 7519114709.31
  },
  {
    "algo": "CAMELLIA-256-CBC",
    "block_size": 256,
    "speed": 7840889344.02
  },
  {
    "algo": "CAMELLIA-256-CBC",
    "block_size": 1024,
    "speed": 7925488639.99
  },
  {
    "algo": "CAMELLIA-256-CBC",
    "block_size": 8192,
    "speed": 7955360426.65
  },
  {
    "algo": "CAMELLIA-256-CBC",
    "block_size": 16384,
    "speed": 7955567957.35
  },
  {
    "algo": "SM4-CBC",
    "block_size": 16,
    "speed": 5893897482.7
  },
  {
    "algo": "SM4-CBC",
    "block_size": 64,
    "speed": 5956102592.01
  },
  {
    "algo": "SM4-CBC",
    "block_size": 256,
    "speed": 5975766783.99
  },
  {
    "algo": "SM4-CBC",
    "block_size": 1024,
    "speed": 5987300352.0
  },
  {
    "algo": "SM4-CBC",
    "block_size": 8192,
    "speed": 5992393386.67
  },
  {
    "algo": "SM4-CBC",
    "block_size": 16384,
    "speed": 5992442538.7
  }
]