[
  {
    "algo": "blake2b512",
    "block_size": 16,
    "speed": 431893728.02
  },
  {
    "algo": "blake2b512",
    "block_size": 64,
    "speed": 1728246357.34
  },
  {
    "algo": "blake2b512",
    "block_size": 256,
    "speed": 4531698773.33
  },
  {
    "algo": "blake2b512",
    "block_size": 1024,
    "speed": 6195665919.98
  },
  {
    "algo": "blake2b512",
    "block_size": 8192,
    "speed": 6930396501.33
  },
  {
    "algo": "blake2b512",
    "block_size": 16384,
    "speed": 6984384512.02
  },
  {
    "algo": "sha256",
    "block_size": 16,
    "speed": 1136266528.0
  },
  {
    "algo": "sha256",
    "block_size": 64,
    "speed": 3843600255.99
  },
  {
    "algo": "sha256",
    "block_size": 256,
    "speed": 9068040533.33
  },
  {
    "algo": "sha256",
    "block_size": 1024,
    "speed": 13745621333.33
  },
  {
    "algo": "sha256",
    "block_size": 8192,
    "speed": 15545996629.34
  },
  {
    "algo": "sha256",
    "block_size": 16384,
    "speed": 15598419967.98
  },
  {
    "algo": "sha512",
    "block_size": 16,
    "speed": 414119296.0
  },
  {
    "algo": "sha512",
    "block_size": 64,
    "speed": 1666206698.68
  },
  {
    "algo": "sha512",
    "block_size": 256,
    "speed": 3258824192.0
  },
  {
    "algo": "sha512",
    "block_size": 1024,
    "speed": 5220295679.99
  },
  {
    "algo": "sha512",
    "block_size": 8192,
    "speed": 6461246122.67
  },
  {
    "algo": "sha512",
    "block_size": 16384,
    "speed": 6575052117.34
  },
  {
    "algo": "sha3-256",
    "block_size": 16,
    "speed": 308809877.33
  },
  {
    "algo": "sha3-256",
    "block_size": 64,
    "speed": 1237703552.02
  },
  {
    "algo": "sha3-256",
    "block_size": 256,
    "speed": 2988138240.01
  },
  {
    "algo": "sha3-256",
    "block_size": 1024,
    "speed": 3496740181.34
  },
  {
    "algo": "sha3-256",
    "block_size": 8192,
    "speed": 3816865792.0
  },
  {
    "algo": "sha3-256",
    "block_size": 16384,
    "speed": 3873188522.67
  },
  {
    "algo": "sha3-512",
    "block_size": 16,
    "speed": 308232330.67
  },
  {
    "algo": "sha3-512",
    "block_size": 64,
    "speed": 1232968319.98
  },
  {
    "algo": "sha3-512",
    "block_size": 256,
    "speed": 1665822122.68
  },
  {
    "algo": "sha3-512",
    "block_size": 1024,
    "speed": 1929421141.34
  },
  {
    "algo": "sha3-512",
    "block_size": 8192,
    "speed": 2091089920.01
  },
  {
    "algo": "sha3-512",
    "block_size": 16384,
    "speed": 2090751317.33
  },
  {
    "algo": "shake128",
    "block_size": 16,
    "speed": 382676975.98
  },
  {
    "algo": "shake128",
    "block_size": 64,
    "speed": 1539376576.02
  },
  {
    "algo": "shake128",
    "block_size": 256,
    "speed": 3398138965.33
  },
  {
    "algo": "shake128",
    "block_size": 1024,
    "speed": 4107029162.66
  },
  {
    "algo": "shake128",
    "block_size": 8192,
    "speed": 4801850425.84
  },
  {
    "algo": "shake128",
    "block_size": 16384,
    "speed": 4842416810.66
  },
  {
    "algo": "shake256",
    "block_size": 16,
    "speed": 391347632.0
  },
  {
    "algo": "shake256",
    "block_size": 64,
    "speed": 1552665088.0
  },
  {
    "algo": "shake256",
    "block_size": 256,
    "speed": 3373613312.02
  },
  {
    "algo": "shake256",
    "block_size": 1024,
    "speed": 3589966848.0
  },
  {
    "algo": "shake256",
    "block_size": 8192,
    "speed": 3842026154.66
  },
  {
    "algo": "shake256",
    "block_size": 16384,
    "speed": 3895918592.01
  },
  {
    "algo": "AES-256-CBC",
    "block_size": 16,
    "speed": 9256681496.21
  },
  {
    "algo": "AES-256-CBC",
    "block_size": 64,
    "speed": 15623344256.01
  },
  {
    "algo": "AES-256-CBC",
    "block_size": 256,
    "speed": 16758658474.69
  },
  {
    "algo": "AES-256-CBC",
    "block_size": 1024,
    "speed": 17460458154.67
  },
  {
    "algo": "AES-256-CBC",
    "block_size": 8192,
    "speed": 17525011797.33
  },
  {
    "algo": "AES-256-CBC",
    "block_size": 16384,
    "speed": 17626502485.33
  },
  {
    "algo": "ARIA-256-CBC",
    "block_size": 16,
    "speed": 1233054549.34
  },
  {
    "algo": "ARIA-256-CBC",
    "block_size": 64,
    "speed": 1284353472.0
  },
  {
    "algo": "ARIA-256-CBC",
    "block_size": 256,
    "speed": 1291997269.32
  },
  {
    "algo": "ARIA-256-CBC",
    "block_size": 1024,
    "speed": 1293235882.67
  },
  {
    "algo": "ARIA-256-CBC",
    "block_size": 8192,
    "speed": 1289521834.68
  },
  {
    "algo": "ARIA-256-CBC",
    "block_size": 16384,
    "speed": 1299551573.33
  },
  {
    "algo": "CAMELLIA-256-CBC",
    "block_size": 16,
    "speed": 1207033482.67
  },
  {
    "algo": "CAMELLIA-256-CBC",
    "block_size": 64,
    "speed": 1585626944.0
  },
  {
    "algo": "CAMELLIA-256-CBC",
    "block_size": 256,
    "speed": 1748112639.99
  },
  {
    "algo": "CAMELLIA-256-CBC",
    "block_size": 1024,
    "speed": 1784859306.66
  },
  {
    "algo": "CAMELLIA-256-CBC",
    "block_size": 8192,
    "speed": 1796358144.0
  },
  {
    "algo": "CAMELLIA-256-CBC",
    "block_size": 16384,
    "speed": 1804577450.67
  },
  {
    "algo": "SM4-CBC",
    "block_size": 16,
    "speed": 1488424532.71
  },
  {
    "algo": "SM4-CBC",
    "block_size": 64,
    "speed": 1541924736.0
  },
  {
    "algo": "SM4-CBC",
    "block_size": 256,
    "speed": 1554151850.67
  },
  {
    "algo": "SM4-CBC",
    "block_size": 1024,
    "speed": 1560170495.98
  },
  {
    "algo": "SM4-CBC",
    "block_size": 8192,
    "speed": 1561000423.61
  },
  {
    "algo": "SM4-CBC",
    "block_size": 16384,
    "speed": 1571822717.89
  }
]