[
  {
    "algo": "blake2b512",
    "block_size": 16,
    "speed": 1472568517.32
  },
  {
    "algo": "blake2b512",
    "block_size": 64,
    "speed": 5903809130.67
  },
  {
    "algo": "blake2b512",
    "block_size": 256,
    "speed": 15456664575.99
  },
  {
    "algo": "blake2b512",
    "block_size": 1024,
    "speed": 21104014677.35
  },
  {
    "algo": "blake2b512",
    "block_size": 8192,
    "speed": 23590668970.65
  },
  {
    "algo": "blake2b512",
    "block_size": 16384,
    "speed": 23720673279.99
  },
  {
    "algo": "sha256",
    "block_size": 16,
    "speed": 3850519690.67
  },
  {
    "algo": "sha256",
    "block_size": 64,
    "speed": 12809861418.68
  },
  {
    "algo": "sha256",
    "block_size": 256,
    "speed": 31034762069.33
  },
  {
    "algo": "sha256",
    "block_size": 1024,
    "speed": 46688896000.01
  },
  {
    "algo": "sha256",
    "block_size": 8192,
    "speed": 52896169984.0
  },
  {
    "algo": "sha256",
    "block_size": 16384,
    "speed": 53206788778.67
  },
  {
    "algo": "sha512",
    "block_size": 16,
    "speed": 1429406778.67
  },
  {
    "algo": "sha512",
    "block_size": 64,
    "speed": 5715187413.3
  },
  {
    "algo": "sha512",
    "block_size": 256,
    "speed": 11234605823.98
  },
  {
    "algo": "sha512",
    "block_size": 1024,
    "speed": 17961742677.35
  },
  {
    "algo": "sha512",
    "block_size": 8192,
    "speed": 22054109184.0
  },
  {
    "algo": "sha512",
    "block_size": 16384,
    "speed": 22455118506.64
  },
  {
    "algo": "sha3-256",
    "block_size": 16,
    "speed": 1058055322.66
  },
  {
    "algo": "sha3-256",
    "block_size": 64,
    "speed": 4234136448.02
  },
  {
    "algo": "sha3-256",
    "block_size": 256,
    "speed": 10220566357.3
  },
  {
    "algo": "sha3-256",
    "block_size": 1024,
    "speed": 11791017642.67
  },
  {
    "algo": "sha3-256",
    "block_size": 8192,
    "speed": 13029892095.97
  },
  {
    "algo": "sha3-256",
    "block_size": 16384,
    "speed": 13225825621.31
  },
  {
    "algo": "sha3-512",
    "block_size": 16,
    "speed": 1050414485.33
  },
  {
    "algo": "sha3-512",
    "block_size": 64,
    "speed": 4211354133.32
  },
  {
    "algo": "sha3-512",
    "block_size": 256,
    "speed": 5719473066.62
  },
  {
    "algo": "sha3-512",
    "block_size": 1024,
    "speed": 6568579754.67
  },
  {
    "algo": "sha3-512",
    "block_size": 8192,
    "speed": 7132569600.02
  },
  {
    "algo": "sha3-512",
    "block_size": 16384,
    "speed": 7157415935.97
  },
  {
    "algo": "shake128",
    "block_size": 16,
    "speed": 1321514549.28
  },
  {
    "algo": "shake128",
    "block_size": 64,
    "speed": 5288054954.67
  },
  {
    "algo": "shake128",
    "block_size": 256,
    "speed": 11558608725.34
  },
  {
    "algo": "shake128",
    "block_size": 1024,
    "speed": 13863374165.36
  },
  {
    "algo": "shake128",
    "block_size": 8192,
    "speed": 16253244757.35
  },
  {
    "algo": "shake128",
    "block_size": 16384,
    "speed": 16345699669.34
  },
  {
    "algo": "shake256",
    "block_size": 16,
    "speed": 1333874378.68
  },
  {
    "algo": "shake256",
    "block_size": 64,
    "speed": 5329645311.98
  },
  {
    "algo": "shake256",
    "block_size": 256,
    "speed": 11581250218.63
  },
  {
    "algo": "shake256",
    "block_size": 1024,
    "speed": 12200115541.34
  },
  {
    "algo": "shake256",
    "block_size": 8192,
    "speed": 13103677440.03
  },
  {
    "algo": "shake256",
    "block_size": 16384,
    "speed": 13276774400.01
  },
  {
    "algo": "AES-256-CBC",
    "block_size": 16,
    "speed": 31402526506.69
  },
  {
    "algo": "AES-256-CBC",
    "block_size": 64,
    "speed": 53601628672.0
  },
  {
    "algo": "AES-256-CBC",
    "block_size": 256,
    "speed": 55758457856.04
  },
  {
    "algo": "AES-256-CBC",
    "block_size": 1024,
    "speed": 58635576320.02
  },
  {
    "algo": "AES-256-CBC",
    "block_size": 8192,
    "speed": 60011151360.0
  },
  {
    "algo": "AES-256-CBC",
    "block_size": 16384,
    "speed": 60167624021.34
  },
  {
    "algo": "ARIA-256-CBC",
    "block_size": 16,
    "speed": 4192400865.29
  },
  {
    "algo": "ARIA-256-CBC",
    "block_size": 64,
    "speed": 4340328554.66
  },
  {
    "algo": "ARIA-256-CBC",
    "block_size": 256,
    "speed": 4383829589.34
  },
  {
    "algo": "ARIA-256-CBC",
    "block_size": 1024,
    "speed": 4391529282.63
  },
  {
    "algo": "ARIA-256-CBC",
    "block_size": 8192,
    "speed": 4396088055.78
  },
  {
    "algo": "ARIA-256-CBC",
    "block_size": 16384,
    "speed": 4395015039.86
  },
  {
    "algo": "CAMELLIA-256-CBC",
    "block_size": 16,
    "speed": 4085675522.64
  },
  {
    "algo": "CAMELLIA-256-CBC",
    "block_size": 64,
    "speed": 5413985535.98
  },
  {
    "algo": "CAMELLIA-256-CBC",
    "block_size": 256,
    "speed": 5913991082.68
  },
  {
    "algo": "CAMELLIA-256-CBC",
    "block_size": 1024,
    "speed": 6053578752.01
  },
  {
    "algo": "CAMELLIA-256-CBC",
    "block_size": 8192,
    "speed": 6093751714.44
  },
  {
    "algo": "CAMELLIA-256-CBC",
    "block_size": 16384,
    "speed": 6092434090.65
  },
  {
    "algo": "SM4-CBC",
    "block_size": 16,
    "speed": 5045525750.03
  },
  {
    "algo": "SM4-CBC",
    "block_size": 64,
    "speed": 5213995242.64
  },
  {
    "algo": "SM4-CBC",
    "block_size": 256,
    "speed": 5284772864.0
  },
  {
    "algo": "SM4-CBC",
    "block_size": 1024,
    "speed": 5303910400.01
  },
  {
    "algo": "SM4-CBC",
    "block_size": 8192,
    "speed": 5311393324.8
  },
  {
    "algo": "SM4-CBC",
    "block_size": 16384,
    "speed": 5308806566.96
  }
]