{"start":"2025-01-14T08:24:10.445090","end":"2025-01-14T08:24:10.445090","exit_code":-1,"error_msg":"1 error occurred:\n\t* creating EC2 Instance: operation error EC2: RunInstances, https response error StatusCode: 400, RequestID: 5a23cdc5-85b4-468d-b215-3525b11ded27, api error VcpuLimitExceeded: You have requested more vCPU capacity than your current vCPU limit of 16 allows for the instance bucket that the specified instance type belongs to. Please visit http://aws.amazon.com/contact-us/ec2-request to request an adjustment to this limit.\n\n\n","task_hash":"5f210f1a2dbfbab7a50d5fb6a1d7a2034445bd38","version":null,"stdout_bytes":null,"stderr_bytes":null,"outputs":[]}