[
  {
    "algo": "blake2b512",
    "block_size": 16,
    "speed": 384120128.0
  },
  {
    "algo": "blake2b512",
    "block_size": 64,
    "speed": 1546851882.68
  },
  {
    "algo": "blake2b512",
    "block_size": 256,
    "speed": 4171124650.67
  },
  {
    "algo": "blake2b512",
    "block_size": 1024,
    "speed": 5923612671.99
  },
  {
    "algo": "blake2b512",
    "block_size": 8192,
    "speed": 7024836608.01
  },
  {
    "algo": "blake2b512",
    "block_size": 16384,
    "speed": 7119519308.55
  },
  {
    "algo": "sha256",
    "block_size": 16,
    "speed": 807156304.0
  },
  {
    "algo": "sha256",
    "block_size": 64,
    "speed": 2617192469.33
  },
  {
    "algo": "sha256",
    "block_size": 256,
    "speed": 6830255189.34
  },
  {
    "algo": "sha256",
    "block_size": 1024,
    "speed": 11475245055.98
  },
  {
    "algo": "sha256",
    "block_size": 8192,
    "speed": 14315836757.32
  },
  {
    "algo": "sha256",
    "block_size": 16384,
    "speed": 14570711722.67
  },
  {
    "algo": "sha512",
    "block_size": 16,
    "speed": 331838288.0
  },
  {
    "algo": "sha512",
    "block_size": 64,
    "speed": 1328075520.0
  },
  {
    "algo": "sha512",
    "block_size": 256,
    "speed": 2717959936.02
  },
  {
    "algo": "sha512",
    "block_size": 1024,
    "speed": 4551647573.34
  },
  {
    "algo": "sha512",
    "block_size": 8192,
    "speed": 5665344170.68
  },
  {
    "algo": "sha512",
    "block_size": 16384,
    "speed": 5755802965.33
  },
  {
    "algo": "sha3-256",
    "block_size": 16,
    "speed": 235707237.33
  },
  {
    "algo": "sha3-256",
    "block_size": 64,
    "speed": 944015807.99
  },
  {
    "algo": "sha3-256",
    "block_size": 256,
    "speed": 2260857685.32
  },
  {
    "algo": "sha3-256",
    "block_size": 1024,
    "speed": 2648952490.67
  },
  {
    "algo": "sha3-256",
    "block_size": 8192,
    "speed": 2924598613.33
  },
  {
    "algo": "sha3-256",
    "block_size": 16384,
    "speed": 2960676181.35
  },
  {
    "algo": "sha3-512",
    "block_size": 16,
    "speed": 236208816.0
  },
  {
    "algo": "sha3-512",
    "block_size": 64,
    "speed": 945040170.65
  },
  {
    "algo": "sha3-512",
    "block_size": 256,
    "speed": 1266511104.0
  },
  {
    "algo": "sha3-512",
    "block_size": 1024,
    "speed": 1469218133.33
  },
  {
    "algo": "sha3-512",
    "block_size": 8192,
    "speed": 1590099968.0
  },
  {
    "algo": "sha3-512",
    "block_size": 16384,
    "speed": 1593731754.66
  },
  {
    "algo": "shake128",
    "block_size": 16,
    "speed": 234242457.2
  },
  {
    "algo": "shake128",
    "block_size": 64,
    "speed": 939122346.66
  },
  {
    "algo": "shake128",
    "block_size": 256,
    "speed": 2248847445.33
  },
  {
    "algo": "shake128",
    "block_size": 1024,
    "speed": 2984152063.99
  },
  {
    "algo": "shake128",
    "block_size": 8192,
    "speed": 3609647255.95
  },
  {
    "algo": "shake128",
    "block_size": 16384,
    "speed": 3626489173.35
  },
  {
    "algo": "shake256",
    "block_size": 16,
    "speed": 232536549.34
  },
  {
    "algo": "shake256",
    "block_size": 64,
    "speed": 928457600.01
  },
  {
    "algo": "shake256",
    "block_size": 256,
    "speed": 2246756352.0
  },
  {
    "algo": "shake256",
    "block_size": 1024,
    "speed": 2645085525.32
  },
  {
    "algo": "shake256",
    "block_size": 8192,
    "speed": 2924388351.99
  },
  {
    "algo": "shake256",
    "block_size": 16384,
    "speed": 2959835136.02
  },
  {
    "algo": "AES-256-CBC",
    "block_size": 16,
    "speed": 5999725509.33
  },
  {
    "algo": "AES-256-CBC",
    "block_size": 64,
    "speed": 11240502314.67
  },
  {
    "algo": "AES-256-CBC",
    "block_size": 256,
    "speed": 14301090389.34
  },
  {
    "algo": "AES-256-CBC",
    "block_size": 1024,
    "speed": 15435862357.34
  },
  {
    "algo": "AES-256-CBC",
    "block_size": 8192,
    "speed": 15797469184.0
  },
  {
    "algo": "AES-256-CBC",
    "block_size": 16384,
    "speed": 15827839658.68
  },
  {
    "algo": "ARIA-256-CBC",
    "block_size": 16,
    "speed": 1025628496.0
  },
  {
    "algo": "ARIA-256-CBC",
    "block_size": 64,
    "speed": 1145145173.32
  },
  {
    "algo": "ARIA-256-CBC",
    "block_size": 256,
    "speed": 1178064640.02
  },
  {
    "algo": "ARIA-256-CBC",
    "block_size": 1024,
    "speed": 1186395477.34
  },
  {
    "algo": "ARIA-256-CBC",
    "block_size": 8192,
    "speed": 1188080298.66
  },
  {
    "algo": "ARIA-256-CBC",
    "block_size": 16384,
    "speed": 1187714389.32
  },
  {
    "algo": "CAMELLIA-256-CBC",
    "block_size": 16,
    "speed": 1050883056.0
  },
  {
    "algo": "CAMELLIA-256-CBC",
    "block_size": 64,
    "speed": 1642477866.66
  },
  {
    "algo": "CAMELLIA-256-CBC",
    "block_size": 256,
    "speed": 1864755029.36
  },
  {
    "algo": "CAMELLIA-256-CBC",
    "block_size": 1024,
    "speed": 1921878698.68
  },
  {
    "algo": "CAMELLIA-256-CBC",
    "block_size": 8192,
    "speed": 1938920789.35
  },
  {
    "algo": "CAMELLIA-256-CBC",
    "block_size": 16384,
    "speed": 1938696874.68
  },
  {
    "algo": "SM4-CBC",
    "block_size": 16,
    "speed": 1457877151.99
  },
  {
    "algo": "SM4-CBC",
    "block_size": 64,
    "speed": 1562048256.01
  },
  {
    "algo": "SM4-CBC",
    "block_size": 256,
    "speed": 1590513407.97
  },
  {
    "algo": "SM4-CBC",
    "block_size": 1024,
    "speed": 1597792597.33
  },
  {
    "algo": "SM4-CBC",
    "block_size": 8192,
    "speed": 1599922175.99
  },
  {
    "algo": "SM4-CBC",
    "block_size": 16384,
    "speed": 1600252586.67
  }
]