[
  {
    "algo": "blake2b512",
    "block_size": 16,
    "speed": 105190533.33
  },
  {
    "algo": "blake2b512",
    "block_size": 64,
    "speed": 423153472.0
  },
  {
    "algo": "blake2b512",
    "block_size": 256,
    "speed": 1089064704.0
  },
  {
    "algo": "blake2b512",
    "block_size": 1024,
    "speed": 1463183018.66
  },
  {
    "algo": "blake2b512",
    "block_size": 8192,
    "speed": 1632138581.33
  },
  {
    "algo": "blake2b512",
    "block_size": 16384,
    "speed": 1633397418.66
  },
  {
    "algo": "sha256",
    "block_size": 16,
    "speed": 278840314.67
  },
  {
    "algo": "sha256",
    "block_size": 64,
    "speed": 917837866.66
  },
  {
    "algo": "sha256",
    "block_size": 256,
    "speed": 2157598976.0
  },
  {
    "algo": "sha256",
    "block_size": 1024,
    "speed": 3273934847.99
  },
  {
    "algo": "sha256",
    "block_size": 8192,
    "speed": 3726772906.66
  },
  {
    "algo": "sha256",
    "block_size": 16384,
    "speed": 3759652864.01
  },
  {
    "algo": "sha512",
    "block_size": 16,
    "speed": 99770981.33
  },
  {
    "algo": "sha512",
    "block_size": 64,
    "speed": 399175872.0
  },
  {
    "algo": "sha512",
    "block_size": 256,
    "speed": 776993024.01
  },
  {
    "algo": "sha512",
    "block_size": 1024,
    "speed": 1253119317.34
  },
  {
    "algo": "sha512",
    "block_size": 8192,
    "speed": 1518135978.67
  },
  {
    "algo": "sha512",
    "block_size": 16384,
    "speed": 1541860010.66
  },
  {
    "algo": "sha3-256",
    "block_size": 16,
    "speed": 74347024.0
  },
  {
    "algo": "sha3-256",
    "block_size": 64,
    "speed": 297615936.01
  },
  {
    "algo": "sha3-256",
    "block_size": 256,
    "speed": 712413439.99
  },
  {
    "algo": "sha3-256",
    "block_size": 1024,
    "speed": 826199381.34
  },
  {
    "algo": "sha3-256",
    "block_size": 8192,
    "speed": 912673450.66
  },
  {
    "algo": "sha3-256",
    "block_size": 16384,
    "speed": 923942912.0
  },
  {
    "algo": "sha3-512",
    "block_size": 16,
    "speed": 73951061.33
  },
  {
    "algo": "sha3-512",
    "block_size": 64,
    "speed": 296615274.68
  },
  {
    "algo": "sha3-512",
    "block_size": 256,
    "speed": 396964010.66
  },
  {
    "algo": "sha3-512",
    "block_size": 1024,
    "speed": 458239317.34
  },
  {
    "algo": "sha3-512",
    "block_size": 8192,
    "speed": 495545002.67
  },
  {
    "algo": "sha3-512",
    "block_size": 16384,
    "speed": 496741034.67
  },
  {
    "algo": "shake128",
    "block_size": 16,
    "speed": 73438890.66
  },
  {
    "algo": "shake128",
    "block_size": 64,
    "speed": 294520341.33
  },
  {
    "algo": "shake128",
    "block_size": 256,
    "speed": 709122645.34
  },
  {
    "algo": "shake128",
    "block_size": 1024,
    "speed": 931294890.66
  },
  {
    "algo": "shake128",
    "block_size": 8192,
    "speed": 1127191893.34
  },
  {
    "algo": "shake128",
    "block_size": 16384,
    "speed": 1133117440.0
  },
  {
    "algo": "shake256",
    "block_size": 16,
    "speed": 73913178.66
  },
  {
    "algo": "shake256",
    "block_size": 64,
    "speed": 295935125.33
  },
  {
    "algo": "shake256",
    "block_size": 256,
    "speed": 710490112.0
  },
  {
    "algo": "shake256",
    "block_size": 1024,
    "speed": 825525930.67
  },
  {
    "algo": "shake256",
    "block_size": 8192,
    "speed": 911764138.67
  },
  {
    "algo": "shake256",
    "block_size": 16384,
    "speed": 923118250.67
  },
  {
    "algo": "AES-256-CBC",
    "block_size": 16,
    "speed": 2260058970.66
  },
  {
    "algo": "AES-256-CBC",
    "block_size": 64,
    "speed": 4094063146.67
  },
  {
    "algo": "AES-256-CBC",
    "block_size": 256,
    "speed": 4085808640.0
  },
  {
    "algo": "AES-256-CBC",
    "block_size": 1024,
    "speed": 4143496874.66
  },
  {
    "algo": "AES-256-CBC",
    "block_size": 8192,
    "speed": 4127460010.67
  },
  {
    "algo": "AES-256-CBC",
    "block_size": 16384,
    "speed": 4031414271.99
  },
  {
    "algo": "ARIA-256-CBC",
    "block_size": 16,
    "speed": 293554965.34
  },
  {
    "algo": "ARIA-256-CBC",
    "block_size": 64,
    "speed": 303883818.66
  },
  {
    "algo": "ARIA-256-CBC",
    "block_size": 256,
    "speed": 306573141.34
  },
  {
    "algo": "ARIA-256-CBC",
    "block_size": 1024,
    "speed": 307398656.0
  },
  {
    "algo": "ARIA-256-CBC",
    "block_size": 8192,
    "speed": 307904512.0
  },
  {
    "algo": "ARIA-256-CBC",
    "block_size": 16384,
    "speed": 307702442.66
  },
  {
    "algo": "CAMELLIA-256-CBC",
    "block_size": 16,
    "speed": 277444901.33
  },
  {
    "algo": "CAMELLIA-256-CBC",
    "block_size": 64,
    "speed": 375312063.99
  },
  {
    "algo": "CAMELLIA-256-CBC",
    "block_size": 256,
    "speed": 411591168.0
  },
  {
    "algo": "CAMELLIA-256-CBC",
    "block_size": 1024,
    "speed": 421629269.33
  },
  {
    "algo": "CAMELLIA-256-CBC",
    "block_size": 8192,
    "speed": 424605013.33
  },
  {
    "algo": "CAMELLIA-256-CBC",
    "block_size": 16384,
    "speed": 424116224.0
  },
  {
    "algo": "SM4-CBC",
    "block_size": 16,
    "speed": 351575498.67
  },
  {
    "algo": "SM4-CBC",
    "block_size": 64,
    "speed": 364482304.01
  },
  {
    "algo": "SM4-CBC",
    "block_size": 256,
    "speed": 369430186.66
  },
  {
    "algo": "SM4-CBC",
    "block_size": 1024,
    "speed": 370902357.34
  },
  {
    "algo": "SM4-CBC",
    "block_size": 8192,
    "speed": 371184981.33
  },
  {
    "algo": "SM4-CBC",
    "block_size": 16384,
    "speed": 370879146.66
  }
]