[
  {
    "algo": "blake2b512",
    "block_size": 16,
    "speed": 941536383.99
  },
  {
    "algo": "blake2b512",
    "block_size": 64,
    "speed": 4300549098.69
  },
  {
    "algo": "blake2b512",
    "block_size": 256,
    "speed": 13244847957.33
  },
  {
    "algo": "blake2b512",
    "block_size": 1024,
    "speed": 20002890410.66
  },
  {
    "algo": "blake2b512",
    "block_size": 8192,
    "speed": 24082740565.36
  },
  {
    "algo": "blake2b512",
    "block_size": 16384,
    "speed": 24263852031.98
  },
  {
    "algo": "sha256",
    "block_size": 16,
    "speed": 2496065370.67
  },
  {
    "algo": "sha256",
    "block_size": 64,
    "speed": 8526650218.66
  },
  {
    "algo": "sha256",
    "block_size": 256,
    "speed": 23359360085.3
  },
  {
    "algo": "sha256",
    "block_size": 1024,
    "speed": 40398421674.68
  },
  {
    "algo": "sha256",
    "block_size": 8192,
    "speed": 50714853375.99
  },
  {
    "algo": "sha256",
    "block_size": 16384,
    "speed": 51618993493.34
  },
  {
    "algo": "sha512",
    "block_size": 16,
    "speed": 1291774624.02
  },
  {
    "algo": "sha512",
    "block_size": 64,
    "speed": 5147376750.29
  },
  {
    "algo": "sha512",
    "block_size": 256,
    "speed": 10577708629.31
  },
  {
    "algo": "sha512",
    "block_size": 1024,
    "speed": 17389513728.0
  },
  {
    "algo": "sha512",
    "block_size": 8192,
    "speed": 21715140607.97
  },
  {
    "algo": "sha512",
    "block_size": 16384,
    "speed": 22194186922.66
  },
  {
    "algo": "sha3-256",
    "block_size": 16,
    "speed": 884982490.68
  },
  {
    "algo": "sha3-256",
    "block_size": 64,
    "speed": 3566247295.98
  },
  {
    "algo": "sha3-256",
    "block_size": 256,
    "speed": 8848813397.35
  },
  {
    "algo": "sha3-256",
    "block_size": 1024,
    "speed": 10852129450.67
  },
  {
    "algo": "sha3-256",
    "block_size": 8192,
    "speed": 12305296042.66
  },
  {
    "algo": "sha3-256",
    "block_size": 16384,
    "speed": 12532127061.32
  },
  {
    "algo": "sha3-512",
    "block_size": 16,
    "speed": 893053653.34
  },
  {
    "algo": "sha3-512",
    "block_size": 64,
    "speed": 3555512149.34
  },
  {
    "algo": "sha3-512",
    "block_size": 256,
    "speed": 5086891520.01
  },
  {
    "algo": "sha3-512",
    "block_size": 1024,
    "speed": 6108113237.3
  },
  {
    "algo": "sha3-512",
    "block_size": 8192,
    "speed": 6715441152.0
  },
  {
    "algo": "sha3-512",
    "block_size": 16384,
    "speed": 6720263509.35
  },
  {
    "algo": "shake128",
    "block_size": 16,
    "speed": 879290309.36
  },
  {
    "algo": "shake128",
    "block_size": 64,
    "speed": 3528967802.47
  },
  {
    "algo": "shake128",
    "block_size": 256,
    "speed": 8821254997.34
  },
  {
    "algo": "shake128",
    "block_size": 1024,
    "speed": 12200943616.0
  },
  {
    "algo": "shake128",
    "block_size": 8192,
    "speed": 14981597866.68
  },
  {
    "algo": "shake128",
    "block_size": 16384,
    "speed": 15184216064.0
  },
  {
    "algo": "shake256",
    "block_size": 16,
    "speed": 888245333.33
  },
  {
    "algo": "shake256",
    "block_size": 64,
    "speed": 3540275690.67
  },
  {
    "algo": "shake256",
    "block_size": 256,
    "speed": 8791897685.34
  },
  {
    "algo": "shake256",
    "block_size": 1024,
    "speed": 10736442709.32
  },
  {
    "algo": "shake256",
    "block_size": 8192,
    "speed": 12117789354.66
  },
  {
    "algo": "shake256",
    "block_size": 16384,
    "speed": 12310069248.01
  },
  {
    "algo": "AES-256-CBC",
    "block_size": 16,
    "speed": 24807899363.97
  },
  {
    "algo": "AES-256-CBC",
    "block_size": 64,
    "speed": 27601404970.68
  },
  {
    "algo": "AES-256-CBC",
    "block_size": 256,
    "speed": 28494089813.33
  },
  {
    "algo": "AES-256-CBC",
    "block_size": 1024,
    "speed": 28677742250.69
  },
  {
    "algo": "AES-256-CBC",
    "block_size": 8192,
    "speed": 28763389952.01
  },
  {
    "algo": "AES-256-CBC",
    "block_size": 16384,
    "speed": 28757677397.33
  },
  {
    "algo": "ARIA-256-CBC",
    "block_size": 16,
    "speed": 3243874152.44
  },
  {
    "algo": "ARIA-256-CBC",
    "block_size": 64,
    "speed": 3390768234.68
  },
  {
    "algo": "ARIA-256-CBC",
    "block_size": 256,
    "speed": 3408129365.35
  },
  {
    "algo": "ARIA-256-CBC",
    "block_size": 1024,
    "speed": 3423865883.39
  },
  {
    "algo": "ARIA-256-CBC",
    "block_size": 8192,
    "speed": 3431185025.87
  },
  {
    "algo": "ARIA-256-CBC",
    "block_size": 16384,
    "speed": 3435637418.66
  },
  {
    "algo": "CAMELLIA-256-CBC",
    "block_size": 16,
    "speed": 3579040373.34
  },
  {
    "algo": "CAMELLIA-256-CBC",
    "block_size": 64,
    "speed": 4279368661.33
  },
  {
    "algo": "CAMELLIA-256-CBC",
    "block_size": 256,
    "speed": 4478699093.34
  },
  {
    "algo": "CAMELLIA-256-CBC",
    "block_size": 1024,
    "speed": 4554296661.34
  },
  {
    "algo": "CAMELLIA-256-CBC",
    "block_size": 8192,
    "speed": 4572984661.32
  },
  {
    "algo": "CAMELLIA-256-CBC",
    "block_size": 16384,
    "speed": 4566505097.79
  },
  {
    "algo": "SM4-CBC",
    "block_size": 16,
    "speed": 3504495926.96
  },
  {
    "algo": "SM4-CBC",
    "block_size": 64,
    "speed": 3607390698.66
  },
  {
    "algo": "SM4-CBC",
    "block_size": 256,
    "speed": 3642022741.32
  },
  {
    "algo": "SM4-CBC",
    "block_size": 1024,
    "speed": 3643546282.66
  },
  {
    "algo": "SM4-CBC",
    "block_size": 8192,
    "speed": 3639225002.69
  },
  {
    "algo": "SM4-CBC",
    "block_size": 16384,
    "speed": 3634757631.99
  }
]