[
  {
    "algo": "blake2b512",
    "block_size": 16,
    "speed": 634915039.98
  },
  {
    "algo": "blake2b512",
    "block_size": 64,
    "speed": 2569317205.33
  },
  {
    "algo": "blake2b512",
    "block_size": 256,
    "speed": 7195204010.66
  },
  {
    "algo": "blake2b512",
    "block_size": 1024,
    "speed": 10589293567.98
  },
  {
    "algo": "blake2b512",
    "block_size": 8192,
    "speed": 12256649216.0
  },
  {
    "algo": "blake2b512",
    "block_size": 16384,
    "speed": 12410994688.0
  },
  {
    "algo": "sha256",
    "block_size": 16,
    "speed": 1261102543.99
  },
  {
    "algo": "sha256",
    "block_size": 64,
    "speed": 4499262250.67
  },
  {
    "algo": "sha256",
    "block_size": 256,
    "speed": 12461757781.35
  },
  {
    "algo": "sha256",
    "block_size": 1024,
    "speed": 22337915904.02
  },
  {
    "algo": "sha256",
    "block_size": 8192,
    "speed": 29140929194.65
  },
  {
    "algo": "sha256",
    "block_size": 16384,
    "speed": 29783976618.67
  },
  {
    "algo": "sha512",
    "block_size": 16,
    "speed": 573962352.01
  },
  {
    "algo": "sha512",
    "block_size": 64,
    "speed": 2302819669.35
  },
  {
    "algo": "sha512",
    "block_size": 256,
    "speed": 4266329258.66
  },
  {
    "algo": "sha512",
    "block_size": 1024,
    "speed": 6519273472.01
  },
  {
    "algo": "sha512",
    "block_size": 8192,
    "speed": 7704783530.67
  },
  {
    "algo": "sha512",
    "block_size": 16384,
    "speed": 7809859584.0
  },
  {
    "algo": "sha3-256",
    "block_size": 16,
    "speed": 448974389.31
  },
  {
    "algo": "sha3-256",
    "block_size": 64,
    "speed": 1799918741.33
  },
  {
    "algo": "sha3-256",
    "block_size": 256,
    "speed": 4450148522.66
  },
  {
    "algo": "sha3-256",
    "block_size": 1024,
    "speed": 5318305109.35
  },
  {
    "algo": "sha3-256",
    "block_size": 8192,
    "speed": 5936534869.34
  },
  {
    "algo": "sha3-256",
    "block_size": 16384,
    "speed": 6014364330.66
  },
  {
    "algo": "sha3-512",
    "block_size": 16,
    "speed": 450636240.0
  },
  {
    "algo": "sha3-512",
    "block_size": 64,
    "speed": 1802059136.01
  },
  {
    "algo": "sha3-512",
    "block_size": 256,
    "speed": 2512878250.67
  },
  {
    "algo": "sha3-512",
    "block_size": 1024,
    "speed": 2953461077.32
  },
  {
    "algo": "sha3-512",
    "block_size": 8192,
    "speed": 3220922368.0
  },
  {
    "algo": "sha3-512",
    "block_size": 16384,
    "speed": 3229362858.66
  },
  {
    "algo": "shake128",
    "block_size": 16,
    "speed": 448306986.66
  },
  {
    "algo": "shake128",
    "block_size": 64,
    "speed": 1795927146.66
  },
  {
    "algo": "shake128",
    "block_size": 256,
    "speed": 4441388800.0
  },
  {
    "algo": "shake128",
    "block_size": 1024,
    "speed": 6018674688.01
  },
  {
    "algo": "shake128",
    "block_size": 8192,
    "speed": 7356137471.99
  },
  {
    "algo": "shake128",
    "block_size": 16384,
    "speed": 7388965546.67
  },
  {
    "algo": "shake256",
    "block_size": 16,
    "speed": 447787215.98
  },
  {
    "algo": "shake256",
    "block_size": 64,
    "speed": 1802675306.67
  },
  {
    "algo": "shake256",
    "block_size": 256,
    "speed": 4448390143.99
  },
  {
    "algo": "shake256",
    "block_size": 1024,
    "speed": 5322355712.0
  },
  {
    "algo": "shake256",
    "block_size": 8192,
    "speed": 5941742250.67
  },
  {
    "algo": "shake256",
    "block_size": 16384,
    "speed": 6009891498.65
  },
  {
    "algo": "AES-256-CBC",
    "block_size": 16,
    "speed": 12650016442.67
  },
  {
    "algo": "AES-256-CBC",
    "block_size": 64,
    "speed": 21406256490.68
  },
  {
    "algo": "AES-256-CBC",
    "block_size": 256,
    "speed": 25485240405.31
  },
  {
    "algo": "AES-256-CBC",
    "block_size": 1024,
    "speed": 26618838357.34
  },
  {
    "algo": "AES-256-CBC",
    "block_size": 8192,
    "speed": 27122903722.67
  },
  {
    "algo": "AES-256-CBC",
    "block_size": 16384,
    "speed": 27172705621.34
  },
  {
    "algo": "ARIA-256-CBC",
    "block_size": 16,
    "speed": 1568019461.33
  },
  {
    "algo": "ARIA-256-CBC",
    "block_size": 64,
    "speed": 1671822037.35
  },
  {
    "algo": "ARIA-256-CBC",
    "block_size": 256,
    "speed": 1696809472.0
  },
  {
    "algo": "ARIA-256-CBC",
    "block_size": 1024,
    "speed": 1705766912.0
  },
  {
    "algo": "ARIA-256-CBC",
    "block_size": 8192,
    "speed": 1710189226.67
  },
  {
    "algo": "ARIA-256-CBC",
    "block_size": 16384,
    "speed": 1710200149.32
  },
  {
    "algo": "CAMELLIA-256-CBC",
    "block_size": 16,
    "speed": 1622860513.5
  },
  {
    "algo": "CAMELLIA-256-CBC",
    "block_size": 64,
    "speed": 1703690197.35
  },
  {
    "algo": "CAMELLIA-256-CBC",
    "block_size": 256,
    "speed": 1726398976.01
  },
  {
    "algo": "CAMELLIA-256-CBC",
    "block_size": 1024,
    "speed": 1735935317.33
  },
  {
    "algo": "CAMELLIA-256-CBC",
    "block_size": 8192,
    "speed": 1736673962.67
  },
  {
    "algo": "CAMELLIA-256-CBC",
    "block_size": 16384,
    "speed": 1736636377.45
  },
  {
    "algo": "SM4-CBC",
    "block_size": 16,
    "speed": 836194565.33
  },
  {
    "algo": "SM4-CBC",
    "block_size": 64,
    "speed": 867081600.02
  },
  {
    "algo": "SM4-CBC",
    "block_size": 256,
    "speed": 874054656.0
  },
  {
    "algo": "SM4-CBC",
    "block_size": 1024,
    "speed": 876640597.36
  },
  {
    "algo": "SM4-CBC",
    "block_size": 8192,
    "speed": 877139285.33
  },
  {
    "algo": "SM4-CBC",
    "block_size": 16384,
    "speed": 876909909.32
  }
]