[
  {
    "algo": "blake2b512",
    "block_size": 16,
    "speed": 1134251045.32
  },
  {
    "algo": "blake2b512",
    "block_size": 64,
    "speed": 4494448789.34
  },
  {
    "algo": "blake2b512",
    "block_size": 256,
    "speed": 12223369642.67
  },
  {
    "algo": "blake2b512",
    "block_size": 1024,
    "speed": 17697344512.03
  },
  {
    "algo": "blake2b512",
    "block_size": 8192,
    "speed": 21115535359.97
  },
  {
    "algo": "blake2b512",
    "block_size": 16384,
    "speed": 21419780778.64
  },
  {
    "algo": "sha256",
    "block_size": 16,
    "speed": 2334076490.65
  },
  {
    "algo": "sha256",
    "block_size": 64,
    "speed": 7607432298.66
  },
  {
    "algo": "sha256",
    "block_size": 256,
    "speed": 20088629333.34
  },
  {
    "algo": "sha256",
    "block_size": 1024,
    "speed": 34054021119.98
  },
  {
    "algo": "sha256",
    "block_size": 8192,
    "speed": 43004406442.66
  },
  {
    "algo": "sha256",
    "block_size": 16384,
    "speed": 43767185408.03
  },
  {
    "algo": "sha512",
    "block_size": 16,
    "speed": 955718826.65
  },
  {
    "algo": "sha512",
    "block_size": 64,
    "speed": 3812226538.64
  },
  {
    "algo": "sha512",
    "block_size": 256,
    "speed": 7892643328.01
  },
  {
    "algo": "sha512",
    "block_size": 1024,
    "speed": 13493107370.66
  },
  {
    "algo": "sha512",
    "block_size": 8192,
    "speed": 17009344512.04
  },
  {
    "algo": "sha512",
    "block_size": 16384,
    "speed": 17292591104.0
  },
  {
    "algo": "sha3-256",
    "block_size": 16,
    "speed": 701109317.34
  },
  {
    "algo": "sha3-256",
    "block_size": 64,
    "speed": 2798401621.34
  },
  {
    "algo": "sha3-256",
    "block_size": 256,
    "speed": 6727728383.98
  },
  {
    "algo": "sha3-256",
    "block_size": 1024,
    "speed": 7954271802.39
  },
  {
    "algo": "sha3-256",
    "block_size": 8192,
    "speed": 8781073066.66
  },
  {
    "algo": "sha3-256",
    "block_size": 16384,
    "speed": 8889998425.57
  },
  {
    "algo": "sha3-512",
    "block_size": 16,
    "speed": 701537365.32
  },
  {
    "algo": "sha3-512",
    "block_size": 64,
    "speed": 2801033258.65
  },
  {
    "algo": "sha3-512",
    "block_size": 256,
    "speed": 3795232597.31
  },
  {
    "algo": "sha3-512",
    "block_size": 1024,
    "speed": 4410810368.03
  },
  {
    "algo": "sha3-512",
    "block_size": 8192,
    "speed": 4775531861.33
  },
  {
    "algo": "sha3-512",
    "block_size": 16384,
    "speed": 4787054603.35
  },
  {
    "algo": "shake128",
    "block_size": 16,
    "speed": 696092032.04
  },
  {
    "algo": "shake128",
    "block_size": 64,
    "speed": 2779939519.97
  },
  {
    "algo": "shake128",
    "block_size": 256,
    "speed": 6684398933.35
  },
  {
    "algo": "shake128",
    "block_size": 1024,
    "speed": 8959063722.67
  },
  {
    "algo": "shake128",
    "block_size": 8192,
    "speed": 10837945002.65
  },
  {
    "algo": "shake128",
    "block_size": 16384,
    "speed": 10892880554.69
  },
  {
    "algo": "shake256",
    "block_size": 16,
    "speed": 698040165.33
  },
  {
    "algo": "shake256",
    "block_size": 64,
    "speed": 2786512490.65
  },
  {
    "algo": "shake256",
    "block_size": 256,
    "speed": 6713352362.68
  },
  {
    "algo": "shake256",
    "block_size": 1024,
    "speed": 7951502335.99
  },
  {
    "algo": "shake256",
    "block_size": 8192,
    "speed": 8779799197.04
  },
  {
    "algo": "shake256",
    "block_size": 16384,
    "speed": 8890451661.86
  },
  {
    "algo": "AES-256-CBC",
    "block_size": 16,
    "speed": 18015496879.98
  },
  {
    "algo": "AES-256-CBC",
    "block_size": 64,
    "speed": 33745727039.99
  },
  {
    "algo": "AES-256-CBC",
    "block_size": 256,
    "speed": 42940259328.0
  },
  {
    "algo": "AES-256-CBC",
    "block_size": 1024,
    "speed": 46314823679.99
  },
  {
    "algo": "AES-256-CBC",
    "block_size": 8192,
    "speed": 47444940117.34
  },
  {
    "algo": "AES-256-CBC",
    "block_size": 16384,
    "speed": 47516549119.99
  },
  {
    "algo": "ARIA-256-CBC",
    "block_size": 16,
    "speed": 3084173975.09
  },
  {
    "algo": "ARIA-256-CBC",
    "block_size": 64,
    "speed": 3439528341.35
  },
  {
    "algo": "ARIA-256-CBC",
    "block_size": 256,
    "speed": 3538189312.0
  },
  {
    "algo": "ARIA-256-CBC",
    "block_size": 1024,
    "speed": 3562185386.65
  },
  {
    "algo": "ARIA-256-CBC",
    "block_size": 8192,
    "speed": 3567740494.8
  },
  {
    "algo": "ARIA-256-CBC",
    "block_size": 16384,
    "speed": 3566281148.49
  },
  {
    "algo": "CAMELLIA-256-CBC",
    "block_size": 16,
    "speed": 3264482185.26
  },
  {
    "algo": "CAMELLIA-256-CBC",
    "block_size": 64,
    "speed": 4980224085.33
  },
  {
    "algo": "CAMELLIA-256-CBC",
    "block_size": 256,
    "speed": 5597048234.73
  },
  {
    "algo": "CAMELLIA-256-CBC",
    "block_size": 1024,
    "speed": 5769746773.33
  },
  {
    "algo": "CAMELLIA-256-CBC",
    "block_size": 8192,
    "speed": 5823228586.67
  },
  {
    "algo": "CAMELLIA-256-CBC",
    "block_size": 16384,
    "speed": 5820681373.62
  },
  {
    "algo": "SM4-CBC",
    "block_size": 16,
    "speed": 4330510112.0
  },
  {
    "algo": "SM4-CBC",
    "block_size": 64,
    "speed": 4675375573.34
  },
  {
    "algo": "SM4-CBC",
    "block_size": 256,
    "speed": 4772267605.36
  },
  {
    "algo": "SM4-CBC",
    "block_size": 1024,
    "speed": 4798118570.67
  },
  {
    "algo": "SM4-CBC",
    "block_size": 8192,
    "speed": 4804378624.01
  },
  {
    "algo": "SM4-CBC",
    "block_size": 16384,
    "speed": 4804968448.01
  }
]