[
  {
    "algo": "blake2b512",
    "block_size": 16,
    "speed": 2717589952.02
  },
  {
    "algo": "blake2b512",
    "block_size": 64,
    "speed": 10883070016.0
  },
  {
    "algo": "blake2b512",
    "block_size": 256,
    "speed": 29859514112.04
  },
  {
    "algo": "blake2b512",
    "block_size": 1024,
    "speed": 44054365866.65
  },
  {
    "algo": "blake2b512",
    "block_size": 8192,
    "speed": 51242336256.0
  },
  {
    "algo": "blake2b512",
    "block_size": 16384,
    "speed": 51821253973.33
  },
  {
    "algo": "sha256",
    "block_size": 16,
    "speed": 6463825354.66
  },
  {
    "algo": "sha256",
    "block_size": 64,
    "speed": 21685349056.0
  },
  {
    "algo": "sha256",
    "block_size": 256,
    "speed": 53752091733.33
  },
  {
    "algo": "sha256",
    "block_size": 1024,
    "speed": 85325149866.66
  },
  {
    "algo": "sha256",
    "block_size": 8192,
    "speed": 102819121834.67
  },
  {
    "algo": "sha256",
    "block_size": 16384,
    "speed": 104348265130.7
  },
  {
    "algo": "sha512",
    "block_size": 16,
    "speed": 3876650601.41
  },
  {
    "algo": "sha512",
    "block_size": 64,
    "speed": 15522935637.32
  },
  {
    "algo": "sha512",
    "block_size": 256,
    "speed": 31993220437.29
  },
  {
    "algo": "sha512",
    "block_size": 1024,
    "speed": 51508869802.68
  },
  {
    "algo": "sha512",
    "block_size": 8192,
    "speed": 62590733478.7
  },
  {
    "algo": "sha512",
    "block_size": 16384,
    "speed": 63524601856.03
  },
  {
    "algo": "sha3-256",
    "block_size": 16,
    "speed": 2101172624.0
  },
  {
    "algo": "sha3-256",
    "block_size": 64,
    "speed": 8416401258.68
  },
  {
    "algo": "sha3-256",
    "block_size": 256,
    "speed": 20491490560.02
  },
  {
    "algo": "sha3-256",
    "block_size": 1024,
    "speed": 24362092202.67
  },
  {
    "algo": "sha3-256",
    "block_size": 8192,
    "speed": 27005307562.68
  },
  {
    "algo": "sha3-256",
    "block_size": 16384,
    "speed": 27347305464.05
  },
  {
    "algo": "sha3-512",
    "block_size": 16,
    "speed": 2098133024.0
  },
  {
    "algo": "sha3-512",
    "block_size": 64,
    "speed": 8400462890.67
  },
  {
    "algo": "sha3-512",
    "block_size": 256,
    "speed": 11524542463.99
  },
  {
    "algo": "sha3-512",
    "block_size": 1024,
    "speed": 13466718218.21
  },
  {
    "algo": "sha3-512",
    "block_size": 8192,
    "speed": 14645100543.98
  },
  {
    "algo": "sha3-512",
    "block_size": 16384,
    "speed": 14678007508.63
  },
  {
    "algo": "shake128",
    "block_size": 16,
    "speed": 2086518661.32
  },
  {
    "algo": "shake128",
    "block_size": 64,
    "speed": 8360535616.02
  },
  {
    "algo": "shake128",
    "block_size": 256,
    "speed": 20409318143.96
  },
  {
    "algo": "shake128",
    "block_size": 1024,
    "speed": 27442445311.99
  },
  {
    "algo": "shake128",
    "block_size": 8192,
    "speed": 33372687018.66
  },
  {
    "algo": "shake128",
    "block_size": 16384,
    "speed": 33560018943.97
  },
  {
    "algo": "shake256",
    "block_size": 16,
    "speed": 2089915365.31
  },
  {
    "algo": "shake256",
    "block_size": 64,
    "speed": 8371624981.33
  },
  {
    "algo": "shake256",
    "block_size": 256,
    "speed": 20406707475.87
  },
  {
    "algo": "shake256",
    "block_size": 1024,
    "speed": 24333532159.99
  },
  {
    "algo": "shake256",
    "block_size": 8192,
    "speed": 27003404288.0
  },
  {
    "algo": "shake256",
    "block_size": 16384,
    "speed": 27350903466.69
  },
  {
    "algo": "AES-256-CBC",
    "block_size": 16,
    "speed": 67614836838.82
  },
  {
    "algo": "AES-256-CBC",
    "block_size": 64,
    "speed": 84684463167.97
  },
  {
    "algo": "AES-256-CBC",
    "block_size": 256,
    "speed": 90944081578.68
  },
  {
    "algo": "AES-256-CBC",
    "block_size": 1024,
    "speed": 93274903552.0
  },
  {
    "algo": "AES-256-CBC",
    "block_size": 8192,
    "speed": 93470550698.66
  },
  {
    "algo": "AES-256-CBC",
    "block_size": 16384,
    "speed": 93641725269.35
  },
  {
    "algo": "ARIA-256-CBC",
    "block_size": 16,
    "speed": 5783135010.13
  },
  {
    "algo": "ARIA-256-CBC",
    "block_size": 64,
    "speed": 5999180181.33
  },
  {
    "algo": "ARIA-256-CBC",
    "block_size": 256,
    "speed": 6057340586.66
  },
  {
    "algo": "ARIA-256-CBC",
    "block_size": 1024,
    "speed": 6068162560.03
  },
  {
    "algo": "ARIA-256-CBC",
    "block_size": 8192,
    "speed": 6069474645.35
  },
  {
    "algo": "ARIA-256-CBC",
    "block_size": 16384,
    "speed": 6069590929.98
  },
  {
    "algo": "CAMELLIA-256-CBC",
    "block_size": 16,
    "speed": 6603610040.4
  },
  {
    "algo": "CAMELLIA-256-CBC",
    "block_size": 64,
    "speed": 6646390421.36
  },
  {
    "algo": "CAMELLIA-256-CBC",
    "block_size": 256,
    "speed": 6648117589.36
  },
  {
    "algo": "CAMELLIA-256-CBC",
    "block_size": 1024,
    "speed": 6656799402.64
  },
  {
    "algo": "CAMELLIA-256-CBC",
    "block_size": 8192,
    "speed": 6656854698.68
  },
  {
    "algo": "CAMELLIA-256-CBC",
    "block_size": 16384,
    "speed": 6656075442.59
  },
  {
    "algo": "SM4-CBC",
    "block_size": 16,
    "speed": 51075210442.62
  },
  {
    "algo": "SM4-CBC",
    "block_size": 64,
    "speed": 61227806485.3
  },
  {
    "algo": "SM4-CBC",
    "block_size": 256,
    "speed": 63143993429.31
  },
  {
    "algo": "SM4-CBC",
    "block_size": 1024,
    "speed": 63642690218.7
  },
  {
    "algo": "SM4-CBC",
    "block_size": 8192,
    "speed": 63793512447.99
  },
  {
    "algo": "SM4-CBC",
    "block_size": 16384,
    "speed": 63798220117.32
  }
]